django_intercooler_helpers-0.2.0.dist-info/DESCRIPTION.rst
django_intercooler_helpers-0.2.0.dist-info/LICENSE.txt
django_intercooler_helpers-0.2.0.dist-info/METADATA
django_intercooler_helpers-0.2.0.dist-info/RECORD
django_intercooler_helpers-0.2.0.dist-info/WHEEL
django_intercooler_helpers-0.2.0.dist-info/metadata.json
django_intercooler_helpers-0.2.0.dist-info/top_level.txt
intercooler_helpers/__init__.py
intercooler_helpers/middleware.py
intercooler_helpers/tests/__init__.py
intercooler_helpers/tests/test_middleware.py
