Metadata-Version: 2.0
Name: django-intercooler-helpers
Version: 0.2.0
Summary: a small reusable app for Django which provides a few improvements for working with Intercooler.js
Home-page: https://github.com/kezabelle/django-intercoolerjs-helpers
Author: Keryn Knight
Author-email: django-intercooler_helpers@kerynknight.com
License: BSD License
Keywords: django intercooler intercoolerjs
Platform: UNKNOWN
Classifier: Development Status :: 3 - Alpha
Classifier: Intended Audience :: Developers
Classifier: License :: OSI Approved :: BSD License
Classifier: Natural Language :: English
Classifier: Programming Language :: Python :: 2
Classifier: Programming Language :: Python :: 2.7
Classifier: Programming Language :: Python :: 3
Classifier: Programming Language :: Python :: 3.3
Classifier: Programming Language :: Python :: 3.4
Classifier: Programming Language :: Python :: 3.5
Classifier: Framework :: Django
Classifier: Framework :: Django :: 1.10
Classifier: Framework :: Django :: 1.8
Classifier: Framework :: Django :: 1.9
Requires-Dist: Django (>=1.8)
Requires-Dist: django-intercoolerjs (>=1.1.0.0)
